{
  "match_id": "1512728",
  "ranking_races": [],
  "milestone_watch": [
    {
      "player": "CN Ackermann",
      "type": "runs",
      "current": 590,
      "target": 600,
      "needed": 10
    },
    {
      "player": "CN Ackermann",
      "type": "fours",
      "current": 43,
      "target": 50,
      "needed": 7
    },
    {
      "player": "M Levitt",
      "type": "runs",
      "current": 957,
      "target": 1000,
      "needed": 43
    },
    {
      "player": "BFW de Leede",
      "type": "runs",
      "current": 881,
      "target": 900,
      "needed": 19
    },
    {
      "player": "RE van der Merwe",
      "type": "fours",
      "current": 40,
      "target": 50,
      "needed": 10
    },
    {
      "player": "SA Edwards",
      "type": "runs",
      "current": 1283,
      "target": 1300,
      "needed": 17
    }
  ],
  "personal_best_watch": []
}