{
  "match_id": "1512721",
  "team_a": "India",
  "team_b": "United States of America",
  "matchups": [
    {
      "bat": "AGS Gous",
      "bat_t": "United States of America",
      "bowl": "Arshdeep Singh",
      "bowl_t": "India",
      "v": "bowler",
      "h2h": {
        "balls": 12,
        "runs": 2,
        "dismissals": 1,
        "strike_rate": 16.67
      },
      "vs_t": {
        "runs": 8,
        "balls": 16,
        "dismissals": 2,
        "average": 4.0,
        "strike_rate": 50.0
      },
      "b_car": {
        "avg": 30.84,
        "sr": 137.43
      },
      "w_car": {
        "avg": 19.63,
        "eco": 8.75
      },
      "b_f": [
        13,
        6
      ],
      "w_f": [
        2,
        0,
        1
      ]
    },
    {
      "bat": "SP Krishnamurthi",
      "bat_t": "United States of America",
      "bowl": "AR Patel",
      "bowl_t": "India",
      "v": "neutral",
      "h2h": {
        "balls": 9,
        "runs": 11,
        "dismissals": 1,
        "strike_rate": 122.22
      },
      "vs_t": {
        "runs": 37,
        "balls": 32,
        "dismissals": 1,
        "average": 37.0,
        "strike_rate": 115.62
      },
      "b_car": {
        "avg": 32.67,
        "sr": 139.01
      },
      "w_car": {
        "avg": 22.41,
        "eco": 7.59
      },
      "b_f": [
        68,
        1,
        0
      ],
      "w_f": [
        2,
        2,
        2
      ]
    },
    {
      "bat": "Milind Kumar",
      "bat_t": "United States of America",
      "bowl": "CV Varun",
      "bowl_t": "India",
      "v": "bowler",
      "h2h": {
        "balls": 9,
        "runs": 4,
        "dismissals": 1,
        "strike_rate": 44.44
      },
      "vs_t": {
        "runs": 34,
        "balls": 34,
        "dismissals": 1,
        "average": 34.0,
        "strike_rate": 100.0
      },
      "b_car": {
        "avg": 32.0,
        "sr": 103.74
      },
      "w_car": {
        "avg": 15.9,
        "eco": 7.36
      },
      "b_f": [
        28,
        3,
        29
      ],
      "w_f": [
        1,
        3,
        2
      ]
    },
    {
      "bat": "AR Patel",
      "bat_t": "India",
      "bowl": "Harmeet Singh",
      "bowl_t": "United States of America",
      "v": "bowler",
      "h2h": {
        "balls": 8,
        "runs": 3,
        "dismissals": 1,
        "strike_rate": 37.5
      },
      "vs_t": {
        "runs": 14,
        "balls": 12,
        "dismissals": 1,
        "average": 14.0,
        "strike_rate": 116.67
      },
      "b_car": {
        "avg": 19.66,
        "sr": 125.55
      },
      "w_car": {
        "avg": 23.35,
        "eco": 7.05
      },
      "b_f": [
        0,
        0,
        14
      ],
      "w_f": [
        0,
        4,
        1
      ]
    },
    {
      "bat": "Shubham Ranjane",
      "bat_t": "United States of America",
      "bowl": "Mohammed Siraj",
      "bowl_t": "India",
      "v": "batsman",
      "h2h": {
        "balls": 7,
        "runs": 10,
        "dismissals": 1,
        "strike_rate": 142.86
      },
      "vs_t": {
        "runs": 37,
        "balls": 23,
        "dismissals": 1,
        "average": 37.0,
        "strike_rate": 160.87
      },
      "b_car": {
        "avg": 70.5,
        "sr": 171.95
      },
      "w_car": {
        "avg": 28.88,
        "eco": 7.92
      },
      "b_f": [
        5,
        48,
        51
      ],
      "w_f": [
        3
      ]
    },
    {
      "bat": "HH Pandya",
      "bat_t": "India",
      "bowl": "Harmeet Singh",
      "bowl_t": "United States of America",
      "v": "bowler",
      "h2h": {
        "balls": 4,
        "runs": 4,
        "dismissals": 1,
        "strike_rate": 100.0
      },
      "vs_t": {
        "runs": 5,
        "balls": 6,
        "dismissals": 1,
        "average": 5.0,
        "strike_rate": 83.33
      },
      "b_car": {
        "avg": 28.12,
        "sr": 138.02
      },
      "w_car": {
        "avg": 23.35,
        "eco": 7.05
      },
      "b_f": [
        18,
        30,
        0
      ],
      "w_f": [
        0,
        4,
        1
      ]
    },
    {
      "bat": "Harmeet Singh",
      "bat_t": "United States of America",
      "bowl": "Arshdeep Singh",
      "bowl_t": "India",
      "v": "neutral",
      "h2h": {
        "balls": 4,
        "runs": 1,
        "dismissals": 1,
        "strike_rate": 25.0
      },
      "vs_t": {
        "runs": 10,
        "balls": 11,
        "dismissals": 2,
        "average": 5.0,
        "strike_rate": 90.91
      },
      "b_car": {
        "avg": 16.13,
        "sr": 139.88
      },
      "w_car": {
        "avg": 19.63,
        "eco": 8.75
      },
      "b_f": [
        1,
        6,
        0
      ],
      "w_f": [
        2,
        0,
        1
      ]
    },
    {
      "bat": "AGS Gous",
      "bat_t": "United States of America",
      "bowl": "Mohammed Siraj",
      "bowl_t": "India",
      "v": "bowler",
      "h2h": {
        "balls": 4,
        "runs": 6,
        "dismissals": 1,
        "strike_rate": 150.0
      },
      "vs_t": {
        "runs": 8,
        "balls": 16,
        "dismissals": 2,
        "average": 4.0,
        "strike_rate": 50.0
      },
      "b_car": {
        "avg": 30.84,
        "sr": 137.43
      },
      "w_car": {
        "avg": 28.88,
        "eco": 7.92
      },
      "b_f": [
        13,
        6
      ],
      "w_f": [
        3
      ]
    },
    {
      "bat": "SR Mukkamalla",
      "bat_t": "United States of America",
      "bowl": "Mohammed Siraj",
      "bowl_t": "India",
      "v": "batsman",
      "h2h": {
        "balls": 2,
        "runs": 2,
        "dismissals": 1,
        "strike_rate": 100.0
      },
      "vs_t": {
        "runs": 2,
        "balls": 7,
        "dismissals": 1,
        "average": 2.0,
        "strike_rate": 28.57
      },
      "b_car": {
        "avg": 40.94,
        "sr": 143.11
      },
      "w_car": {
        "avg": 28.88,
        "eco": 7.92
      },
      "b_f": [
        17,
        79,
        2
      ],
      "w_f": [
        3
      ]
    },
    {
      "bat": "Abhishek Sharma",
      "bat_t": "India",
      "bowl": "Ali Khan",
      "bowl_t": "United States of America",
      "v": "batsman",
      "h2h": {
        "balls": 1,
        "runs": 0,
        "dismissals": 1,
        "strike_rate": 0.0
      },
      "vs_t": {
        "runs": 0,
        "balls": 1,
        "dismissals": 1,
        "average": 0.0,
        "strike_rate": 0.0
      },
      "b_car": {
        "avg": 35.46,
        "sr": 184.27
      },
      "w_car": {
        "avg": 37.76,
        "eco": 9.15
      },
      "b_f": [
        15,
        0,
        0
      ],
      "w_f": [
        1,
        0,
        1
      ]
    },
    {
      "bat": "Harmeet Singh",
      "bat_t": "United States of America",
      "bowl": "AR Patel",
      "bowl_t": "India",
      "v": "bowler",
      "h2h": {
        "balls": 1,
        "runs": 0,
        "dismissals": 1,
        "strike_rate": 0.0
      },
      "vs_t": {
        "runs": 10,
        "balls": 11,
        "dismissals": 2,
        "average": 5.0,
        "strike_rate": 90.91
      },
      "b_car": {
        "avg": 16.13,
        "sr": 139.88
      },
      "w_car": {
        "avg": 22.41,
        "eco": 7.59
      },
      "b_f": [
        1,
        6,
        0
      ],
      "w_f": [
        2,
        2,
        2
      ]
    },
    {
      "bat": "MD Patel",
      "bat_t": "United States of America",
      "bowl": "Arshdeep Singh",
      "bowl_t": "India",
      "v": "neutral",
      "h2h": {
        "balls": 1,
        "runs": 0,
        "dismissals": 1,
        "strike_rate": 0.0
      },
      "vs_t": {
        "runs": 0,
        "balls": 2,
        "dismissals": 1,
        "average": 0.0,
        "strike_rate": 0.0
      },
      "b_car": {
        "avg": 28.89,
        "sr": 132.68
      },
      "w_car": {
        "avg": 19.63,
        "eco": 8.75
      },
      "b_f": [
        52,
        36,
        3
      ],
      "w_f": [
        2,
        0,
        1
      ]
    },
    {
      "bat": "RK Singh",
      "bat_t": "India",
      "bowl": "Mohammad Mohsin",
      "bowl_t": "United States of America",
      "v": "neutral",
      "h2h": {
        "balls": 10,
        "runs": 2,
        "dismissals": 1,
        "strike_rate": 20.0
      },
      "vs_t": {
        "runs": 6,
        "balls": 14,
        "dismissals": 1,
        "average": 6.0,
        "strike_rate": 42.86
      },
      "b_car": {
        "avg": 28.1,
        "sr": 136.57
      },
      "b_f": [
        0,
        6,
        11
      ],
      "w_f": [
        0,
        2,
        1
      ]
    },
    {
      "bat": "S Dube",
      "bat_t": "India",
      "bowl": "SC van Schalkwyk",
      "bowl_t": "United States of America",
      "v": "batsman",
      "h2h": {
        "balls": 8,
        "runs": 5,
        "dismissals": 1,
        "strike_rate": 62.5
      },
      "vs_t": {
        "runs": 31,
        "balls": 38,
        "dismissals": 1,
        "average": 31.0,
        "strike_rate": 81.58
      },
      "b_car": {
        "avg": 31.2,
        "sr": 141.3
      },
      "b_f": [
        42,
        66,
        27
      ],
      "w_f": [
        2,
        3,
        4
      ]
    },
    {
      "bat": "Tilak Varma",
      "bat_t": "India",
      "bowl": "SC van Schalkwyk",
      "bowl_t": "United States of America",
      "v": "batsman",
      "h2h": {
        "balls": 6,
        "runs": 8,
        "dismissals": 1,
        "strike_rate": 133.33
      },
      "vs_t": {
        "runs": 25,
        "balls": 16,
        "dismissals": 1,
        "average": 25.0,
        "strike_rate": 156.25
      },
      "b_car": {
        "avg": 46.81,
        "sr": 136.65
      },
      "b_f": [
        1,
        31,
        25
      ],
      "w_f": [
        2,
        3,
        4
      ]
    },
    {
      "bat": "Ishan Kishan",
      "bat_t": "India",
      "bowl": "SC van Schalkwyk",
      "bowl_t": "United States of America",
      "v": "neutral",
      "h2h": {
        "balls": 3,
        "runs": 1,
        "dismissals": 1,
        "strike_rate": 33.33
      },
      "vs_t": {
        "runs": 20,
        "balls": 16,
        "dismissals": 1,
        "average": 20.0,
        "strike_rate": 125.0
      },
      "b_car": {
        "avg": 29.68,
        "sr": 138.02
      },
      "b_f": [
        0,
        18,
        77
      ],
      "w_f": [
        2,
        3,
        4
      ]
    },
    {
      "bat": "Mohammad Mohsin",
      "bat_t": "United States of America",
      "bowl": "Arshdeep Singh",
      "bowl_t": "India",
      "v": "neutral",
      "h2h": {
        "balls": 3,
        "runs": 5,
        "dismissals": 1,
        "strike_rate": 166.67
      },
      "vs_t": {
        "runs": 8,
        "balls": 9,
        "dismissals": 1,
        "average": 8.0,
        "strike_rate": 88.89
      },
      "w_car": {
        "avg": 19.63,
        "eco": 8.75
      },
      "b_f": [
        1,
        0,
        8
      ],
      "w_f": [
        2,
        0,
        1
      ]
    },
    {
      "bat": "Arshdeep Singh",
      "bat_t": "India",
      "bowl": "SC van Schalkwyk",
      "bowl_t": "United States of America",
      "v": "neutral",
      "h2h": {
        "balls": 2,
        "runs": 0,
        "dismissals": 1,
        "strike_rate": 0.0
      },
      "vs_t": {
        "runs": 4,
        "balls": 7,
        "dismissals": 1,
        "average": 4.0,
        "strike_rate": 57.14
      },
      "b_car": {
        "avg": 7.25,
        "sr": 98.86
      },
      "b_f": [
        1,
        2,
        4
      ],
      "w_f": [
        2,
        3,
        4
      ]
    },
    {
      "bat": "SA Yadav",
      "bat_t": "India",
      "bowl": "SN Netravalkar",
      "bowl_t": "United States of America",
      "v": "batsman",
      "h2h": {
        "balls": 21,
        "runs": 45,
        "dismissals": 0,
        "strike_rate": 214.29
      },
      "vs_t": {
        "runs": 134,
        "balls": 99,
        "dismissals": 0,
        "average": 134.0,
        "strike_rate": 135.35
      },
      "b_car": {
        "avg": 38.51,
        "sr": 156.8
      },
      "w_car": {
        "avg": 25.79,
        "eco": 7.44
      },
      "b_f": [
        18,
        34,
        32
      ],
      "w_f": [
        1,
        1,
        0
      ]
    },
    {
      "bat": "SA Yadav",
      "bat_t": "India",
      "bowl": "SC van Schalkwyk",
      "bowl_t": "United States of America",
      "v": "batsman",
      "h2h": {
        "balls": 28,
        "runs": 33,
        "dismissals": 0,
        "strike_rate": 117.86
      },
      "vs_t": {
        "runs": 134,
        "balls": 99,
        "dismissals": 0,
        "average": 134.0,
        "strike_rate": 135.35
      },
      "b_car": {
        "avg": 38.51,
        "sr": 156.8
      },
      "b_f": [
        18,
        34,
        32
      ],
      "w_f": [
        2,
        3,
        4
      ]
    },
    {
      "bat": "SP Krishnamurthi",
      "bat_t": "United States of America",
      "bowl": "CV Varun",
      "bowl_t": "India",
      "v": "neutral",
      "h2h": {
        "balls": 11,
        "runs": 13,
        "dismissals": 0,
        "strike_rate": 118.18
      },
      "vs_t": {
        "runs": 37,
        "balls": 32,
        "dismissals": 1,
        "average": 37.0,
        "strike_rate": 115.62
      },
      "b_car": {
        "avg": 32.67,
        "sr": 139.01
      },
      "w_car": {
        "avg": 15.9,
        "eco": 7.36
      },
      "b_f": [
        68,
        1,
        0
      ],
      "w_f": [
        1,
        3,
        2
      ]
    },
    {
      "bat": "SA Yadav",
      "bat_t": "India",
      "bowl": "Harmeet Singh",
      "bowl_t": "United States of America",
      "v": "batsman",
      "h2h": {
        "balls": 9,
        "runs": 12,
        "dismissals": 0,
        "strike_rate": 133.33
      },
      "vs_t": {
        "runs": 134,
        "balls": 99,
        "dismissals": 0,
        "average": 134.0,
        "strike_rate": 135.35
      },
      "b_car": {
        "avg": 38.51,
        "sr": 156.8
      },
      "w_car": {
        "avg": 23.35,
        "eco": 7.05
      },
      "b_f": [
        18,
        34,
        32
      ],
      "w_f": [
        0,
        4,
        1
      ]
    },
    {
      "bat": "SA Yadav",
      "bat_t": "India",
      "bowl": "Shubham Ranjane",
      "bowl_t": "United States of America",
      "v": "batsman",
      "h2h": {
        "balls": 9,
        "runs": 14,
        "dismissals": 0,
        "strike_rate": 155.56
      },
      "vs_t": {
        "runs": 134,
        "balls": 99,
        "dismissals": 0,
        "average": 134.0,
        "strike_rate": 135.35
      },
      "b_car": {
        "avg": 38.51,
        "sr": 156.8
      },
      "w_car": {
        "avg": 26.0,
        "eco": 6.5
      },
      "b_f": [
        18,
        34,
        32
      ],
      "w_f": [
        1,
        0,
        0
      ]
    },
    {
      "bat": "S Dube",
      "bat_t": "India",
      "bowl": "Ali Khan",
      "bowl_t": "United States of America",
      "v": "batsman",
      "h2h": {
        "balls": 9,
        "runs": 4,
        "dismissals": 0,
        "strike_rate": 44.44
      },
      "vs_t": {
        "runs": 31,
        "balls": 38,
        "dismissals": 1,
        "average": 31.0,
        "strike_rate": 81.58
      },
      "b_car": {
        "avg": 31.2,
        "sr": 141.3
      },
      "w_car": {
        "avg": 37.76,
        "eco": 9.15
      },
      "b_f": [
        42,
        66,
        27
      ],
      "w_f": [
        1,
        0,
        1
      ]
    },
    {
      "bat": "Milind Kumar",
      "bat_t": "United States of America",
      "bowl": "AR Patel",
      "bowl_t": "India",
      "v": "bowler",
      "h2h": {
        "balls": 9,
        "runs": 9,
        "dismissals": 0,
        "strike_rate": 100.0
      },
      "vs_t": {
        "runs": 34,
        "balls": 34,
        "dismissals": 1,
        "average": 34.0,
        "strike_rate": 100.0
      },
      "b_car": {
        "avg": 32.0,
        "sr": 103.74
      },
      "w_car": {
        "avg": 22.41,
        "eco": 7.59
      },
      "b_f": [
        28,
        3,
        29
      ],
      "w_f": [
        2,
        2,
        2
      ]
    },
    {
      "bat": "Shubham Ranjane",
      "bat_t": "United States of America",
      "bowl": "HH Pandya",
      "bowl_t": "India",
      "v": "batsman",
      "h2h": {
        "balls": 8,
        "runs": 16,
        "dismissals": 0,
        "strike_rate": 200.0
      },
      "vs_t": {
        "runs": 37,
        "balls": 23,
        "dismissals": 1,
        "average": 37.0,
        "strike_rate": 160.87
      },
      "b_car": {
        "avg": 70.5,
        "sr": 171.95
      },
      "w_car": {
        "avg": 27.46,
        "eco": 8.49
      },
      "b_f": [
        5,
        48,
        51
      ],
      "w_f": [
        0,
        1,
        2
      ]
    },
    {
      "bat": "Ishan Kishan",
      "bat_t": "India",
      "bowl": "SN Netravalkar",
      "bowl_t": "United States of America",
      "v": "neutral",
      "h2h": {
        "balls": 7,
        "runs": 8,
        "dismissals": 0,
        "strike_rate": 114.29
      },
      "vs_t": {
        "runs": 20,
        "balls": 16,
        "dismissals": 1,
        "average": 20.0,
        "strike_rate": 125.0
      },
      "b_car": {
        "avg": 29.68,
        "sr": 138.02
      },
      "w_car": {
        "avg": 25.79,
        "eco": 7.44
      },
      "b_f": [
        0,
        18,
        77
      ],
      "w_f": [
        1,
        1,
        0
      ]
    },
    {
      "bat": "Milind Kumar",
      "bat_t": "United States of America",
      "bowl": "Mohammed Siraj",
      "bowl_t": "India",
      "v": "neutral",
      "h2h": {
        "balls": 7,
        "runs": 8,
        "dismissals": 0,
        "strike_rate": 114.29
      },
      "vs_t": {
        "runs": 34,
        "balls": 34,
        "dismissals": 1,
        "average": 34.0,
        "strike_rate": 100.0
      },
      "b_car": {
        "avg": 32.0,
        "sr": 103.74
      },
      "w_car": {
        "avg": 28.88,
        "eco": 7.92
      },
      "b_f": [
        28,
        3,
        29
      ],
      "w_f": [
        3
      ]
    },
    {
      "bat": "Ishan Kishan",
      "bat_t": "India",
      "bowl": "Ali Khan",
      "bowl_t": "United States of America",
      "v": "batsman",
      "h2h": {
        "balls": 6,
        "runs": 11,
        "dismissals": 0,
        "strike_rate": 183.33
      },
      "vs_t": {
        "runs": 20,
        "balls": 16,
        "dismissals": 1,
        "average": 20.0,
        "strike_rate": 125.0
      },
      "b_car": {
        "avg": 29.68,
        "sr": 138.02
      },
      "w_car": {
        "avg": 37.76,
        "eco": 9.15
      },
      "b_f": [
        0,
        18,
        77
      ],
      "w_f": [
        1,
        0,
        1
      ]
    },
    {
      "bat": "SP Krishnamurthi",
      "bat_t": "United States of America",
      "bowl": "HH Pandya",
      "bowl_t": "India",
      "v": "batsman",
      "h2h": {
        "balls": 6,
        "runs": 9,
        "dismissals": 0,
        "strike_rate": 150.0
      },
      "vs_t": {
        "runs": 37,
        "balls": 32,
        "dismissals": 1,
        "average": 37.0,
        "strike_rate": 115.62
      },
      "b_car": {
        "avg": 32.67,
        "sr": 139.01
      },
      "w_car": {
        "avg": 27.46,
        "eco": 8.49
      },
      "b_f": [
        68,
        1,
        0
      ],
      "w_f": [
        0,
        1,
        2
      ]
    },
    {
      "bat": "Tilak Varma",
      "bat_t": "India",
      "bowl": "Ali Khan",
      "bowl_t": "United States of America",
      "v": "batsman",
      "h2h": {
        "balls": 5,
        "runs": 2,
        "dismissals": 0,
        "strike_rate": 40.0
      },
      "vs_t": {
        "runs": 25,
        "balls": 16,
        "dismissals": 1,
        "average": 25.0,
        "strike_rate": 156.25
      },
      "b_car": {
        "avg": 46.81,
        "sr": 136.65
      },
      "w_car": {
        "avg": 37.76,
        "eco": 9.15
      },
      "b_f": [
        1,
        31,
        25
      ],
      "w_f": [
        1,
        0,
        1
      ]
    },
    {
      "bat": "Tilak Varma",
      "bat_t": "India",
      "bowl": "SN Netravalkar",
      "bowl_t": "United States of America",
      "v": "batsman",
      "h2h": {
        "balls": 5,
        "runs": 15,
        "dismissals": 0,
        "strike_rate": 300.0
      },
      "vs_t": {
        "runs": 25,
        "balls": 16,
        "dismissals": 1,
        "average": 25.0,
        "strike_rate": 156.25
      },
      "b_car": {
        "avg": 46.81,
        "sr": 136.65
      },
      "w_car": {
        "avg": 25.79,
        "eco": 7.44
      },
      "b_f": [
        1,
        31,
        25
      ],
      "w_f": [
        1,
        1,
        0
      ]
    },
    {
      "bat": "SR Mukkamalla",
      "bat_t": "United States of America",
      "bowl": "Arshdeep Singh",
      "bowl_t": "India",
      "v": "batsman",
      "h2h": {
        "balls": 5,
        "runs": 0,
        "dismissals": 0,
        "strike_rate": 0.0
      },
      "vs_t": {
        "runs": 2,
        "balls": 7,
        "dismissals": 1,
        "average": 2.0,
        "strike_rate": 28.57
      },
      "b_car": {
        "avg": 40.94,
        "sr": 143.11
      },
      "w_car": {
        "avg": 19.63,
        "eco": 8.75
      },
      "b_f": [
        17,
        79,
        2
      ],
      "w_f": [
        2,
        0,
        1
      ]
    },
    {
      "bat": "SC van Schalkwyk",
      "bat_t": "United States of America",
      "bowl": "Mohammed Siraj",
      "bowl_t": "India",
      "v": "neutral",
      "h2h": {
        "balls": 5,
        "runs": 7,
        "dismissals": 0,
        "strike_rate": 140.0
      },
      "vs_t": {
        "runs": 13,
        "balls": 15,
        "dismissals": 0,
        "average": 13.0,
        "strike_rate": 86.67
      },
      "b_car": {
        "avg": 21.4,
        "sr": 109.18
      },
      "w_car": {
        "avg": 28.88,
        "eco": 7.92
      },
      "b_f": [
        1,
        2
      ],
      "w_f": [
        3
      ]
    },
    {
      "bat": "Milind Kumar",
      "bat_t": "United States of America",
      "bowl": "Arshdeep Singh",
      "bowl_t": "India",
      "v": "neutral",
      "h2h": {
        "balls": 5,
        "runs": 8,
        "dismissals": 0,
        "strike_rate": 160.0
      },
      "vs_t": {
        "runs": 34,
        "balls": 34,
        "dismissals": 1,
        "average": 34.0,
        "strike_rate": 100.0
      },
      "b_car": {
        "avg": 32.0,
        "sr": 103.74
      },
      "w_car": {
        "avg": 19.63,
        "eco": 8.75
      },
      "b_f": [
        28,
        3,
        29
      ],
      "w_f": [
        2,
        0,
        1
      ]
    },
    {
      "bat": "SA Yadav",
      "bat_t": "India",
      "bowl": "Ali Khan",
      "bowl_t": "United States of America",
      "v": "batsman",
      "h2h": {
        "balls": 4,
        "runs": 7,
        "dismissals": 0,
        "strike_rate": 175.0
      },
      "vs_t": {
        "runs": 134,
        "balls": 99,
        "dismissals": 0,
        "average": 134.0,
        "strike_rate": 135.35
      },
      "b_car": {
        "avg": 38.51,
        "sr": 156.8
      },
      "w_car": {
        "avg": 37.76,
        "eco": 9.15
      },
      "b_f": [
        18,
        34,
        32
      ],
      "w_f": [
        1,
        0,
        1
      ]
    },
    {
      "bat": "AR Patel",
      "bat_t": "India",
      "bowl": "SN Netravalkar",
      "bowl_t": "United States of America",
      "v": "neutral",
      "h2h": {
        "balls": 4,
        "runs": 11,
        "dismissals": 0,
        "strike_rate": 275.0
      },
      "vs_t": {
        "runs": 14,
        "balls": 12,
        "dismissals": 1,
        "average": 14.0,
        "strike_rate": 116.67
      },
      "b_car": {
        "avg": 19.66,
        "sr": 125.55
      },
      "w_car": {
        "avg": 25.79,
        "eco": 7.44
      },
      "b_f": [
        0,
        0,
        14
      ],
      "w_f": [
        1,
        1,
        0
      ]
    },
    {
      "bat": "SP Krishnamurthi",
      "bat_t": "United States of America",
      "bowl": "Mohammed Siraj",
      "bowl_t": "India",
      "v": "batsman",
      "h2h": {
        "balls": 4,
        "runs": 2,
        "dismissals": 0,
        "strike_rate": 50.0
      },
      "vs_t": {
        "runs": 37,
        "balls": 32,
        "dismissals": 1,
        "average": 37.0,
        "strike_rate": 115.62
      },
      "b_car": {
        "avg": 32.67,
        "sr": 139.01
      },
      "w_car": {
        "avg": 28.88,
        "eco": 7.92
      },
      "b_f": [
        68,
        1,
        0
      ],
      "w_f": [
        3
      ]
    },
    {
      "bat": "Harmeet Singh",
      "bat_t": "United States of America",
      "bowl": "HH Pandya",
      "bowl_t": "India",
      "v": "neutral",
      "h2h": {
        "balls": 4,
        "runs": 0,
        "dismissals": 0,
        "strike_rate": 0.0
      },
      "vs_t": {
        "runs": 10,
        "balls": 11,
        "dismissals": 2,
        "average": 5.0,
        "strike_rate": 90.91
      },
      "b_car": {
        "avg": 16.13,
        "sr": 139.88
      },
      "w_car": {
        "avg": 27.46,
        "eco": 8.49
      },
      "b_f": [
        1,
        6,
        0
      ],
      "w_f": [
        0,
        1,
        2
      ]
    },
    {
      "bat": "SC van Schalkwyk",
      "bat_t": "United States of America",
      "bowl": "HH Pandya",
      "bowl_t": "India",
      "v": "neutral",
      "h2h": {
        "balls": 4,
        "runs": 1,
        "dismissals": 0,
        "strike_rate": 25.0
      },
      "vs_t": {
        "runs": 13,
        "balls": 15,
        "dismissals": 0,
        "average": 13.0,
        "strike_rate": 86.67
      },
      "b_car": {
        "avg": 21.4,
        "sr": 109.18
      },
      "w_car": {
        "avg": 27.46,
        "eco": 8.49
      },
      "b_f": [
        1,
        2
      ],
      "w_f": [
        0,
        1,
        2
      ]
    },
    {
      "bat": "SC van Schalkwyk",
      "bat_t": "United States of America",
      "bowl": "Arshdeep Singh",
      "bowl_t": "India",
      "v": "neutral",
      "h2h": {
        "balls": 4,
        "runs": 3,
        "dismissals": 0,
        "strike_rate": 75.0
      },
      "vs_t": {
        "runs": 13,
        "balls": 15,
        "dismissals": 0,
        "average": 13.0,
        "strike_rate": 86.67
      },
      "b_car": {
        "avg": 21.4,
        "sr": 109.18
      },
      "w_car": {
        "avg": 19.63,
        "eco": 8.75
      },
      "b_f": [
        1,
        2
      ],
      "w_f": [
        2,
        0,
        1
      ]
    },
    {
      "bat": "Milind Kumar",
      "bat_t": "United States of America",
      "bowl": "HH Pandya",
      "bowl_t": "India",
      "v": "neutral",
      "h2h": {
        "balls": 4,
        "runs": 5,
        "dismissals": 0,
        "strike_rate": 125.0
      },
      "vs_t": {
        "runs": 34,
        "balls": 34,
        "dismissals": 1,
        "average": 34.0,
        "strike_rate": 100.0
      },
      "b_car": {
        "avg": 32.0,
        "sr": 103.74
      },
      "w_car": {
        "avg": 27.46,
        "eco": 8.49
      },
      "b_f": [
        28,
        3,
        29
      ],
      "w_f": [
        0,
        1,
        2
      ]
    },
    {
      "bat": "Shubham Ranjane",
      "bat_t": "United States of America",
      "bowl": "CV Varun",
      "bowl_t": "India",
      "v": "batsman",
      "h2h": {
        "balls": 4,
        "runs": 7,
        "dismissals": 0,
        "strike_rate": 175.0
      },
      "vs_t": {
        "runs": 37,
        "balls": 23,
        "dismissals": 1,
        "average": 37.0,
        "strike_rate": 160.87
      },
      "b_car": {
        "avg": 70.5,
        "sr": 171.95
      },
      "w_car": {
        "avg": 15.9,
        "eco": 7.36
      },
      "b_f": [
        5,
        48,
        51
      ],
      "w_f": [
        1,
        3,
        2
      ]
    },
    {
      "bat": "Arshdeep Singh",
      "bat_t": "India",
      "bowl": "Shubham Ranjane",
      "bowl_t": "United States of America",
      "v": "neutral",
      "h2h": {
        "balls": 3,
        "runs": 0,
        "dismissals": 0,
        "strike_rate": 0.0
      },
      "vs_t": {
        "runs": 4,
        "balls": 7,
        "dismissals": 1,
        "average": 4.0,
        "strike_rate": 57.14
      },
      "b_car": {
        "avg": 7.25,
        "sr": 98.86
      },
      "w_car": {
        "avg": 26.0,
        "eco": 6.5
      },
      "b_f": [
        1,
        2,
        4
      ],
      "w_f": [
        1,
        0,
        0
      ]
    },
    {
      "bat": "Shubham Ranjane",
      "bat_t": "United States of America",
      "bowl": "AR Patel",
      "bowl_t": "India",
      "v": "batsman",
      "h2h": {
        "balls": 3,
        "runs": 3,
        "dismissals": 0,
        "strike_rate": 100.0
      },
      "vs_t": {
        "runs": 37,
        "balls": 23,
        "dismissals": 1,
        "average": 37.0,
        "strike_rate": 160.87
      },
      "b_car": {
        "avg": 70.5,
        "sr": 171.95
      },
      "w_car": {
        "avg": 22.41,
        "eco": 7.59
      },
      "b_f": [
        5,
        48,
        51
      ],
      "w_f": [
        2,
        2,
        2
      ]
    },
    {
      "bat": "SA Yadav",
      "bat_t": "India",
      "bowl": "Mohammad Mohsin",
      "bowl_t": "United States of America",
      "v": "batsman",
      "h2h": {
        "balls": 12,
        "runs": 13,
        "dismissals": 0,
        "strike_rate": 108.33
      },
      "vs_t": {
        "runs": 134,
        "balls": 99,
        "dismissals": 0,
        "average": 134.0,
        "strike_rate": 135.35
      },
      "b_car": {
        "avg": 38.51,
        "sr": 156.8
      },
      "b_f": [
        18,
        34,
        32
      ],
      "w_f": [
        0,
        2,
        1
      ]
    },
    {
      "bat": "RK Singh",
      "bat_t": "India",
      "bowl": "Harmeet Singh",
      "bowl_t": "United States of America",
      "v": "bowler",
      "h2h": {
        "balls": 2,
        "runs": 2,
        "dismissals": 0,
        "strike_rate": 100.0
      },
      "vs_t": {
        "runs": 6,
        "balls": 14,
        "dismissals": 1,
        "average": 6.0,
        "strike_rate": 42.86
      },
      "b_car": {
        "avg": 28.1,
        "sr": 136.57
      },
      "w_car": {
        "avg": 23.35,
        "eco": 7.05
      },
      "b_f": [
        0,
        6,
        11
      ],
      "w_f": [
        0,
        4,
        1
      ]
    },
    {
      "bat": "Arshdeep Singh",
      "bat_t": "India",
      "bowl": "Harmeet Singh",
      "bowl_t": "United States of America",
      "v": "bowler",
      "h2h": {
        "balls": 2,
        "runs": 4,
        "dismissals": 0,
        "strike_rate": 200.0
      },
      "vs_t": {
        "runs": 4,
        "balls": 7,
        "dismissals": 1,
        "average": 4.0,
        "strike_rate": 57.14
      },
      "b_car": {
        "avg": 7.25,
        "sr": 98.86
      },
      "w_car": {
        "avg": 23.35,
        "eco": 7.05
      },
      "b_f": [
        1,
        2,
        4
      ],
      "w_f": [
        0,
        4,
        1
      ]
    },
    {
      "bat": "SP Krishnamurthi",
      "bat_t": "United States of America",
      "bowl": "Arshdeep Singh",
      "bowl_t": "India",
      "v": "batsman",
      "h2h": {
        "balls": 2,
        "runs": 2,
        "dismissals": 0,
        "strike_rate": 100.0
      },
      "vs_t": {
        "runs": 37,
        "balls": 32,
        "dismissals": 1,
        "average": 37.0,
        "strike_rate": 115.62
      },
      "b_car": {
        "avg": 32.67,
        "sr": 139.01
      },
      "w_car": {
        "avg": 19.63,
        "eco": 8.75
      },
      "b_f": [
        68,
        1,
        0
      ],
      "w_f": [
        2,
        0,
        1
      ]
    },
    {
      "bat": "RK Singh",
      "bat_t": "India",
      "bowl": "Shubham Ranjane",
      "bowl_t": "United States of America",
      "v": "neutral",
      "h2h": {
        "balls": 1,
        "runs": 1,
        "dismissals": 0,
        "strike_rate": 100.0
      },
      "vs_t": {
        "runs": 6,
        "balls": 14,
        "dismissals": 1,
        "average": 6.0,
        "strike_rate": 42.86
      },
      "b_car": {
        "avg": 28.1,
        "sr": 136.57
      },
      "w_car": {
        "avg": 26.0,
        "eco": 6.5
      },
      "b_f": [
        0,
        6,
        11
      ],
      "w_f": [
        1,
        0,
        0
      ]
    }
  ]
}